beiwe_har/__init__.py
beiwe_har/config.py
beiwe_har/pipeline.py
beiwe_har/schemas.py
beiwe_har/features/__init__.py
beiwe_har/features/activity_level.py
beiwe_har/features/ecdf.py
beiwe_har/features/uci_har.py
beiwe_har/models/__init__.py
beiwe_har/models/har_model.py
beiwe_har/models/random_forest_ecdf.pkl
beiwe_har/outputs/__init__.py
beiwe_har/outputs/phone_position.py
beiwe_har/outputs/summary.py
beiwe_har/preprocessing/__init__.py
beiwe_har/preprocessing/dataset.py
beiwe_har/preprocessing/segmentation.py
beiwe_har-0.0.1.dist-info/METADATA
beiwe_har-0.0.1.dist-info/WHEEL
beiwe_har-0.0.1.dist-info/top_level.txt
beiwe_har-0.0.1.dist-info/RECORD
