Metadata-Version: 2.4
Name: beiwe-har
Version: 0.0.1
Summary: Beiwe study → preprocessing → segmentation → features → HAR → outputs
Requires-Python: >=3.9
Requires-Dist: numpy>=1.23
Requires-Dist: pandas>=2.0
Requires-Dist: scipy>=1.10
Requires-Dist: scikit-learn>=1.2
Requires-Dist: joblib>=1.3
Requires-Dist: pyarrow>=14
Requires-Dist: geopy>=2.3
Requires-Dist: tqdm>=4.66
Provides-Extra: geo
Requires-Dist: shapely>=2.0; extra == "geo"
